raise_sdk/__init__.py
raise_sdk/code_checker/__init__.py
raise_sdk/code_checker/main.py
raise_sdk/code_checker/flake8/__init__.py
raise_sdk/code_checker/flake8/check.py
raise_sdk/code_checker/flake8/flake8-config.ini
raise_sdk/code_checker/flake8/plugin.py
raise_sdk/code_checker/ruff/__init__.py
raise_sdk/code_checker/ruff/check.py
raise_sdk/revo/LocalCodeRunner.py
raise_sdk/revo/__init__.py
raise_sdk/revo/main.py
raise_sdk/revo/templates.py
raise_sdk/revo/app/CodeRunner.py
raise_sdk/revo/app/__init__.py
raise_sdk/revo/app/main.py
raise_sdk/revo/app/supervisord.log
raise_sdk/revo/app/__pycache__/CodeRunner.cpython-311.pyc
raise_sdk/revo/app/__pycache__/__init__.cpython-311.pyc
raise_sdk/revo/app/code_runner_files/AbstractCodeRunner.py
raise_sdk/revo/app/code_runner_files/Config.py
raise_sdk/revo/app/code_runner_files/Dataset.py
raise_sdk/revo/app/code_runner_files/LoadData.py
raise_sdk/revo/app/code_runner_files/LogClass.py
raise_sdk/revo/app/code_runner_files/MinioClient.py
raise_sdk/revo/app/code_runner_files/ResultsObject.py
raise_sdk/revo/app/code_runner_files/Runner.py
raise_sdk/revo/app/code_runner_files/custom_exceptions.py
raise_sdk/revo/app/code_runner_files/__pycache__/Config.cpython-311.pyc
raise_sdk/revo/app/code_runner_files/__pycache__/MinioClient.cpython-311.pyc
raise_sdk/revo/app/code_runner_files/__pycache__/custom_exceptions.cpython-311.pyc
raise_sdk/utils/__init__.py
raise_sdk/utils/file_utils.py
raise_sdk/utils/ui_dialogs.py
raise_sdk-0.2.9.dist-info/licenses/LICENSE
tests/__init__.py
tests/conftest.py
tests/test_code_converter.py
tests/test_revo_main.py
tests/test_revo_runner.py
raise_sdk-0.2.9.dist-info/METADATA
raise_sdk-0.2.9.dist-info/WHEEL
raise_sdk-0.2.9.dist-info/entry_points.txt
raise_sdk-0.2.9.dist-info/top_level.txt
raise_sdk-0.2.9.dist-info/RECORD
