Metadata-Version: 2.4
Name: raise_sdk
Version: 0.2.9
Summary: RAISE Software Development Kit
Home-page: https://repo.raise-science.eu/raise_dev/raise-sdk
Author: RAISE
Author-email: info@raise-science.eu
Classifier: Programming Language :: Python :: 3
Classifier: License :: OSI Approved :: European Union Public Licence 1.2 (EUPL 1.2)
Classifier: Operating System :: OS Independent
Classifier: Development Status :: 4 - Beta
Requires-Python: >=3.8, <4
License-File: LICENSE
Requires-Dist: docker==7.1.0
Requires-Dist: minio==7.1.0
Requires-Dist: PyQt5
Requires-Dist: ruff>=0.12.2
Requires-Dist: flake8>=7.3.0
Requires-Dist: pre-commit>=4.2.0
Provides-Extra: test
Requires-Dist: pytest>=6.0; extra == "test"
Dynamic: author
Dynamic: author-email
Dynamic: classifier
Dynamic: description
Dynamic: description-content-type
Dynamic: home-page
Dynamic: license-file
Dynamic: provides-extra
Dynamic: requires-dist
Dynamic: requires-python
Dynamic: summary
